[
  {
    "title": "C++",
    "imageSrc": "skills/cpp.png"
  },
  {
    "title": "HTML",
    "imageSrc": "skills/html.png"
  },
  {
    "title": "CSS",
    "imageSrc": "skills/css.png"
  },
  {
    "title": "JavaScript",
    "imageSrc": "skills/js.png"
  },
  {
    "title": "TypeScript",
    "imageSrc": "skills/ts.png"
  },
  {
    "title": "Tailwind",
    "imageSrc": "skills/tailwind.png"
  },
  {
    "title": "React",
    "imageSrc": "skills/react.png"
  },
  {
    "title": "NextJS",
    "imageSrc": "skills/nextjs.png"
  },
  {
    "title": "Node",
    "imageSrc": "skills/node.png"
  },
  {
    "title": "NestJs",
    "imageSrc": "skills/nestjs.png"
  },
  {
    "title": "MongoDB",
    "imageSrc": "skills/mongodb.png"
  }
]